docedian/__init__.py
docedian/data.py
docedian/utils.py
docedian/base/__init__.py
docedian/base/base.py
docedian/facturacion/__init__.py
docedian/facturacion/base.py
docedian/nomina/__init__.py
docedian/nomina/base.py
docedian-0.1.7.dist-info/LICENSE.txt
docedian-0.1.7.dist-info/METADATA
docedian-0.1.7.dist-info/WHEEL
docedian-0.1.7.dist-info/top_level.txt
docedian-0.1.7.dist-info/RECORD
