Metadata-Version: 2.1
Name: docedian
Version: 0.1.7
Summary: Modulo con definiciones de la DIAN
Home-page: https://github.com/pedroporras/dian_technical_data
Author: Pedro Porras
Author-email: <pedroporras@inexpresivo.com>
License: MIT
Keywords: DIAN,Colombia
License-File: LICENSE.txt
Provides-Extra: dev
Provides-Extra: test
